"branch_time/__init__,py"
branch_time/GitRepositoryError.py
branch_time/jira.py
branch_time-0.1.4.dist-info/entry_points.txt
branch_time-0.1.4.dist-info/LICENSE
branch_time-0.1.4.dist-info/METADATA
branch_time-0.1.4.dist-info/WHEEL
branch_time-0.1.4.dist-info/RECORD
