Metadata-Version: 2.1
Name: branch-time
Version: 0.1.4
Summary: Counts time in a branch
License: Beerware
Author: Icaro Nunes
Requires-Python: >=3.8.0,<4
Classifier: Development Status :: 4 - Beta
Classifier: Environment :: Console
Classifier: License :: Other/Proprietary License
Classifier: Programming Language :: Python :: 3
Classifier: Programming Language :: Python :: 3.8
Classifier: Programming Language :: Python :: 3.9
Classifier: Programming Language :: Python :: 3.10
Classifier: Programming Language :: Python :: 3.11
Requires-Dist: click (>=8.0,<9.0)
Requires-Dist: pytest (>=7.3.1,<8.0.0)
Requires-Dist: rich (>=13.3.4,<14.0.0)
Requires-Dist: typer (>=0.7.0,<0.8.0)
Requires-Dist: typer-cli (>=0.0.13,<0.0.14)
Project-URL: Bug Tracker, https://github.com/icaronunes/branch-time/issues
Project-URL: Repository, https://github.com/icaronunes/branch-time
